discqueue/__init__.py
discqueue/core.cpython-311-darwin.so
discqueue-0.1.0.dist-info/LICENCE.txt
discqueue-0.1.0.dist-info/METADATA
discqueue-0.1.0.dist-info/WHEEL
discqueue-0.1.0.dist-info/top_level.txt
discqueue-0.1.0.dist-info/RECORD
