Metadata-Version: 2.1
Name: discqueue
Version: 0.1.0
Author: YY
Author-email: 
Classifier: Programming Language :: Python :: 3
Classifier: License :: OSI Approved :: MIT License
Classifier: Operating System :: OS Independent
Requires-Python: >=3.6
License-File: LICENCE.txt
Requires-Dist: matplotlib
Requires-Dist: numpy
Requires-Dist: cython
